<?xml version="1.0" encoding="utf-8"?>
<Deputados>
  <Deputado>
    <numLegislatura>53</numLegislatura>
    <email>
    </email>
    <nomeProfissao>Jornalista</nomeProfissao>
    <dataNascimento>23/04/1959</dataNascimento>
    <dataFalecimento>
    </dataFalecimento>
    <ufRepresentacaoAtual>MG</ufRepresentacaoAtual>
    <situacaoNaLegislaturaAtual>L</situacaoNaLegislaturaAtual>
    <ideCadastro>74108</ideCadastro>
    <idParlamentarDeprecated>3274</idParlamentarDeprecated>
    <nomeParlamentarAtual>NARCIO RODRIGUES</nomeParlamentarAtual>
    <nomeCivil>NÁRCIO RODRIGUES DA SILVEIRA</nomeCivil>
    <sexo>M</sexo>
    <partidoAtual>
      <idPartido>PSDB</idPartido>
      <sigla>PSDB</sigla>
      <nome>Partido da Social Democracia Brasileira</nome>
    </partidoAtual>
    <gabinete>
      <numero>
      </numero>
      <anexo>
      </anexo>
      <telefone>
      </telefone>
    </gabinete>
    <comissoes>
      <comissao>
        <idOrgaoLegislativoCD>2009</idOrgaoLegislativoCD>
        <siglaComissao>CE</siglaComissao>
        <nomeComissao>Comissão de Educação</nomeComissao>
        <condicaoMembro>Suplente</condicaoMembro>
        <dataEntrada>04/03/2009</dataEntrada>
        <dataSaida>01/02/2010</dataSaida>
      </comissao>
      <comissao>
        <idOrgaoLegislativoCD>2003</idOrgaoLegislativoCD>
        <siglaComissao>CCJC</siglaComissao>
        <nomeComissao>Comissão de Constituição e Justiça e de Cidadania</nomeComissao>
        <condicaoMembro>Suplente</condicaoMembro>
        <dataEntrada>03/03/2010</dataEntrada>
        <dataSaida>31/01/2011</dataSaida>
      </comissao>
      <comissao>
        <idOrgaoLegislativoCD>2009</idOrgaoLegislativoCD>
        <siglaComissao>CE</siglaComissao>
        <nomeComissao>Comissão de Educação</nomeComissao>
        <condicaoMembro>Suplente</condicaoMembro>
        <dataEntrada>03/03/2010</dataEntrada>
        <dataSaida>31/01/2011</dataSaida>
      </comissao>
      <comissao>
        <idOrgaoLegislativoCD>5418</idOrgaoLegislativoCD>
        <siglaComissao>MESA</siglaComissao>
        <nomeComissao>Mesa Diretora da Câmara dos Deputados</nomeComissao>
        <condicaoMembro>Titular</condicaoMembro>
        <dataEntrada>01/02/2007</dataEntrada>
        <dataSaida>02/02/2009</dataSaida>
      </comissao>
      <comissao>
        <idOrgaoLegislativoCD>2002</idOrgaoLegislativoCD>
        <siglaComissao>CCTCI</siglaComissao>
        <nomeComissao>Comissão de Ciência e Tecnologia, Comunicação e Informática</nomeComissao>
        <condicaoMembro>Titular</condicaoMembro>
        <dataEntrada>04/03/2009</dataEntrada>
        <dataSaida>01/02/2010</dataSaida>
      </comissao>
      <comissao>
        <idOrgaoLegislativoCD>536720</idOrgaoLegislativoCD>
        <siglaComissao>CMO-09</siglaComissao>
        <nomeComissao>Comissão Mista de Planos, Orçamentos Públicos e Fiscalização - CMO</nomeComissao>
        <condicaoMembro>Titular</condicaoMembro>
        <dataEntrada>24/03/2009</dataEntrada>
        <dataSaida>30/03/2010</dataSaida>
      </comissao>
      <comissao>
        <idOrgaoLegislativoCD>536781</idOrgaoLegislativoCD>
        <siglaComissao>SUBACEXE</siglaComissao>
        <nomeComissao>Subcomissão Especial de Acompanhamento da Execução Orçamentária.</nomeComissao>
        <condicaoMembro>Titular</condicaoMembro>
        <dataEntrada>08/04/2009</dataEntrada>
        <dataSaida>31/01/2011</dataSaida>
      </comissao>
      <comissao>
        <idOrgaoLegislativoCD>536698</idOrgaoLegislativoCD>
        <siglaComissao>CPI-DIVI</siglaComissao>
        <nomeComissao>Comissão Parlamentar de Inquérito destinada a investigar a dívida pública da União, Estados e Municípios, o pagamento de juros da mesma, os beneficiários destes pagamentos e o seu impacto nas políticas sociais e no desenvolvimento sustentável do País.</nomeComissao>
        <condicaoMembro>Titular</condicaoMembro>
        <dataEntrada>20/08/2009</dataEntrada>
        <dataSaida>25/08/2009</dataSaida>
      </comissao>
      <comissao>
        <idOrgaoLegislativoCD>536783</idOrgaoLegislativoCD>
        <siglaComissao>CPITAELE</siglaComissao>
        <nomeComissao>Comissão Parlamentar de Inquérito destinada a investigar a formação dos valores das tarifas de energia elétrica no Brasil, a atuação da Agência Nacional de Energia Elétrica (ANEEL) na autorização dos reajustes e reposicionamentos tarifários a título de reequilíbrio econômico-financeiro e esclarecer os motivos pelos quais a tarifa média de energia elétrica no Brasil ser maior do que em nações do chamado G7, grupo dos 7 países mais desenvolvidos do mundo.</nomeComissao>
        <condicaoMembro>Titular</condicaoMembro>
        <dataEntrada>25/08/2009</dataEntrada>
        <dataSaida>30/11/2009</dataSaida>
      </comissao>
      <comissao>
        <idOrgaoLegislativoCD>2002</idOrgaoLegislativoCD>
        <siglaComissao>CCTCI</siglaComissao>
        <nomeComissao>Comissão de Ciência e Tecnologia, Comunicação e Informática</nomeComissao>
        <condicaoMembro>Titular</condicaoMembro>
        <dataEntrada>03/03/2010</dataEntrada>
        <dataSaida>31/01/2011</dataSaida>
      </comissao>
    </comissoes>
    <cargosComissoes>
      <cargoComissoes>
        <idOrgaoLegislativoCD>5418</idOrgaoLegislativoCD>
        <siglaComissao>MESA</siglaComissao>
        <nomeComissao>Mesa Diretora da Câmara dos Deputados</nomeComissao>
        <idCargo>2</idCargo>
        <nomeCargo>1º Vice-Presidente</nomeCargo>
        <dataEntrada>01/02/2007</dataEntrada>
        <dataSaida>02/02/2009</dataSaida>
      </cargoComissoes>
      <cargoComissoes>
        <idOrgaoLegislativoCD>536781</idOrgaoLegislativoCD>
        <siglaComissao>SUBACEXE</siglaComissao>
        <nomeComissao>Subcomissão Especial de Acompanhamento da Execução Orçamentária.</nomeComissao>
        <idCargo>1</idCargo>
        <nomeCargo>Presidente</nomeCargo>
        <dataEntrada>14/05/2009</dataEntrada>
        <dataSaida>31/01/2011</dataSaida>
      </cargoComissoes>
    </cargosComissoes>
    <periodosExercicio>
      <periodoExercicio>
        <siglaUFRepresentacao>MG</siglaUFRepresentacao>
        <situacaoExercicio>Titular</situacaoExercicio>
        <dataInicio>01/02/2007</dataInicio>
        <dataFim>03/01/2011</dataFim>
        <idCausaFimExercicio>12</idCausaFimExercicio>
        <descricaoCausaFimExercicio>Secretário de Estado</descricaoCausaFimExercicio>
        <idCadastroParlamentarAnterior>
        </idCadastroParlamentarAnterior>
      </periodoExercicio>
      <periodoExercicio>
        <siglaUFRepresentacao>MG</siglaUFRepresentacao>
        <situacaoExercicio>Titular</situacaoExercicio>
        <dataInicio>01/02/2011</dataInicio>
        <dataFim>02/02/2011</dataFim>
        <idCausaFimExercicio>12</idCausaFimExercicio>
        <descricaoCausaFimExercicio>Secretário de Estado</descricaoCausaFimExercicio>
        <idCadastroParlamentarAnterior>
        </idCadastroParlamentarAnterior>
      </periodoExercicio>
      <periodoExercicio>
        <siglaUFRepresentacao>MG</siglaUFRepresentacao>
        <situacaoExercicio>Titular</situacaoExercicio>
        <dataInicio>01/11/2013</dataInicio>
        <dataFim>
        </dataFim>
        <idCausaFimExercicio>
        </idCausaFimExercicio>
        <descricaoCausaFimExercicio>
        </descricaoCausaFimExercicio>
        <idCadastroParlamentarAnterior>
        </idCadastroParlamentarAnterior>
      </periodoExercicio>
    </periodosExercicio>
    <historicoNomeParlamentar />
    <filiacoesPartidarias />
    <historicoLider>
      <itemHistoricoLider>
        <idHistoricoLider>74108</idHistoricoLider>
        <idCargoLideranca>V</idCargoLideranca>
        <descricaoCargoLideranca>Vice-Líder</descricaoCargoLideranca>
        <numOrdemCargo>38</numOrdemCargo>
        <dataDesignacao>25/11/2009</dataDesignacao>
        <dataTermino>12/03/2010</dataTermino>
        <codigoUnidadeLideranca>P</codigoUnidadeLideranca>
        <siglaUnidadeLideranca>PSDB</siglaUnidadeLideranca>
        <idBlocoPartido>PSDB</idBlocoPartido>
      </itemHistoricoLider>
    </historicoLider>
  </Deputado>
  <Deputado>
    <numLegislatura>54</numLegislatura>
    <email>dep.narciorodrigues@camara.gov.br</email>
    <nomeProfissao>Jornalista</nomeProfissao>
    <dataNascimento>23/04/1959</dataNascimento>
    <dataFalecimento>
    </dataFalecimento>
    <ufRepresentacaoAtual>MG</ufRepresentacaoAtual>
    <situacaoNaLegislaturaAtual>E</situacaoNaLegislaturaAtual>
    <ideCadastro>74108</ideCadastro>
    <idParlamentarDeprecated>3274</idParlamentarDeprecated>
    <nomeParlamentarAtual>NARCIO RODRIGUES</nomeParlamentarAtual>
    <nomeCivil>NÁRCIO RODRIGUES DA SILVEIRA</nomeCivil>
    <sexo>M</sexo>
    <partidoAtual>
      <idPartido>PSDB</idPartido>
      <sigla>PSDB</sigla>
      <nome>Partido da Social Democracia Brasileira</nome>
    </partidoAtual>
    <gabinete>
      <numero>431</numero>
      <anexo>4</anexo>
      <telefone>3215-5431</telefone>
    </gabinete>
    <comissoes>
      <comissao>
        <idOrgaoLegislativoCD>2009</idOrgaoLegislativoCD>
        <siglaComissao>CE</siglaComissao>
        <nomeComissao>Comissão de Educação</nomeComissao>
        <condicaoMembro>Suplente</condicaoMembro>
        <dataEntrada>04/03/2009</dataEntrada>
        <dataSaida>01/02/2010</dataSaida>
      </comissao>
      <comissao>
        <idOrgaoLegislativoCD>2003</idOrgaoLegislativoCD>
        <siglaComissao>CCJC</siglaComissao>
        <nomeComissao>Comissão de Constituição e Justiça e de Cidadania</nomeComissao>
        <condicaoMembro>Suplente</condicaoMembro>
        <dataEntrada>03/03/2010</dataEntrada>
        <dataSaida>31/01/2011</dataSaida>
      </comissao>
      <comissao>
        <idOrgaoLegislativoCD>2009</idOrgaoLegislativoCD>
        <siglaComissao>CE</siglaComissao>
        <nomeComissao>Comissão de Educação</nomeComissao>
        <condicaoMembro>Suplente</condicaoMembro>
        <dataEntrada>03/03/2010</dataEntrada>
        <dataSaida>31/01/2011</dataSaida>
      </comissao>
      <comissao>
        <idOrgaoLegislativoCD>5418</idOrgaoLegislativoCD>
        <siglaComissao>MESA</siglaComissao>
        <nomeComissao>Mesa Diretora da Câmara dos Deputados</nomeComissao>
        <condicaoMembro>Titular</condicaoMembro>
        <dataEntrada>01/02/2007</dataEntrada>
        <dataSaida>02/02/2009</dataSaida>
      </comissao>
      <comissao>
        <idOrgaoLegislativoCD>2002</idOrgaoLegislativoCD>
        <siglaComissao>CCTCI</siglaComissao>
        <nomeComissao>Comissão de Ciência e Tecnologia, Comunicação e Informática</nomeComissao>
        <condicaoMembro>Titular</condicaoMembro>
        <dataEntrada>04/03/2009</dataEntrada>
        <dataSaida>01/02/2010</dataSaida>
      </comissao>
      <comissao>
        <idOrgaoLegislativoCD>536720</idOrgaoLegislativoCD>
        <siglaComissao>CMO-09</siglaComissao>
        <nomeComissao>Comissão Mista de Planos, Orçamentos Públicos e Fiscalização - CMO</nomeComissao>
        <condicaoMembro>Titular</condicaoMembro>
        <dataEntrada>24/03/2009</dataEntrada>
        <dataSaida>30/03/2010</dataSaida>
      </comissao>
      <comissao>
        <idOrgaoLegislativoCD>536781</idOrgaoLegislativoCD>
        <siglaComissao>SUBACEXE</siglaComissao>
        <nomeComissao>Subcomissão Especial de Acompanhamento da Execução Orçamentária.</nomeComissao>
        <condicaoMembro>Titular</condicaoMembro>
        <dataEntrada>08/04/2009</dataEntrada>
        <dataSaida>31/01/2011</dataSaida>
      </comissao>
      <comissao>
        <idOrgaoLegislativoCD>536698</idOrgaoLegislativoCD>
        <siglaComissao>CPI-DIVI</siglaComissao>
        <nomeComissao>Comissão Parlamentar de Inquérito destinada a investigar a dívida pública da União, Estados e Municípios, o pagamento de juros da mesma, os beneficiários destes pagamentos e o seu impacto nas políticas sociais e no desenvolvimento sustentável do País.</nomeComissao>
        <condicaoMembro>Titular</condicaoMembro>
        <dataEntrada>20/08/2009</dataEntrada>
        <dataSaida>25/08/2009</dataSaida>
      </comissao>
      <comissao>
        <idOrgaoLegislativoCD>536783</idOrgaoLegislativoCD>
        <siglaComissao>CPITAELE</siglaComissao>
        <nomeComissao>Comissão Parlamentar de Inquérito destinada a investigar a formação dos valores das tarifas de energia elétrica no Brasil, a atuação da Agência Nacional de Energia Elétrica (ANEEL) na autorização dos reajustes e reposicionamentos tarifários a título de reequilíbrio econômico-financeiro e esclarecer os motivos pelos quais a tarifa média de energia elétrica no Brasil ser maior do que em nações do chamado G7, grupo dos 7 países mais desenvolvidos do mundo.</nomeComissao>
        <condicaoMembro>Titular</condicaoMembro>
        <dataEntrada>25/08/2009</dataEntrada>
        <dataSaida>30/11/2009</dataSaida>
      </comissao>
      <comissao>
        <idOrgaoLegislativoCD>2002</idOrgaoLegislativoCD>
        <siglaComissao>CCTCI</siglaComissao>
        <nomeComissao>Comissão de Ciência e Tecnologia, Comunicação e Informática</nomeComissao>
        <condicaoMembro>Titular</condicaoMembro>
        <dataEntrada>03/03/2010</dataEntrada>
        <dataSaida>31/01/2011</dataSaida>
      </comissao>
    </comissoes>
    <cargosComissoes>
      <cargoComissoes>
        <idOrgaoLegislativoCD>5418</idOrgaoLegislativoCD>
        <siglaComissao>MESA</siglaComissao>
        <nomeComissao>Mesa Diretora da Câmara dos Deputados</nomeComissao>
        <idCargo>2</idCargo>
        <nomeCargo>1º Vice-Presidente</nomeCargo>
        <dataEntrada>01/02/2007</dataEntrada>
        <dataSaida>02/02/2009</dataSaida>
      </cargoComissoes>
      <cargoComissoes>
        <idOrgaoLegislativoCD>536781</idOrgaoLegislativoCD>
        <siglaComissao>SUBACEXE</siglaComissao>
        <nomeComissao>Subcomissão Especial de Acompanhamento da Execução Orçamentária.</nomeComissao>
        <idCargo>1</idCargo>
        <nomeCargo>Presidente</nomeCargo>
        <dataEntrada>14/05/2009</dataEntrada>
        <dataSaida>31/01/2011</dataSaida>
      </cargoComissoes>
    </cargosComissoes>
    <periodosExercicio>
      <periodoExercicio>
        <siglaUFRepresentacao>MG</siglaUFRepresentacao>
        <situacaoExercicio>Titular</situacaoExercicio>
        <dataInicio>01/02/2007</dataInicio>
        <dataFim>03/01/2011</dataFim>
        <idCausaFimExercicio>12</idCausaFimExercicio>
        <descricaoCausaFimExercicio>Secretário de Estado</descricaoCausaFimExercicio>
        <idCadastroParlamentarAnterior>
        </idCadastroParlamentarAnterior>
      </periodoExercicio>
      <periodoExercicio>
        <siglaUFRepresentacao>MG</siglaUFRepresentacao>
        <situacaoExercicio>Titular</situacaoExercicio>
        <dataInicio>01/02/2011</dataInicio>
        <dataFim>02/02/2011</dataFim>
        <idCausaFimExercicio>12</idCausaFimExercicio>
        <descricaoCausaFimExercicio>Secretário de Estado</descricaoCausaFimExercicio>
        <idCadastroParlamentarAnterior>
        </idCadastroParlamentarAnterior>
      </periodoExercicio>
      <periodoExercicio>
        <siglaUFRepresentacao>MG</siglaUFRepresentacao>
        <situacaoExercicio>Titular</situacaoExercicio>
        <dataInicio>01/11/2013</dataInicio>
        <dataFim>
        </dataFim>
        <idCausaFimExercicio>
        </idCausaFimExercicio>
        <descricaoCausaFimExercicio>
        </descricaoCausaFimExercicio>
        <idCadastroParlamentarAnterior>
        </idCadastroParlamentarAnterior>
      </periodoExercicio>
    </periodosExercicio>
    <historicoNomeParlamentar />
    <filiacoesPartidarias />
    <historicoLider>
      <itemHistoricoLider>
        <idHistoricoLider>74108</idHistoricoLider>
        <idCargoLideranca>V</idCargoLideranca>
        <descricaoCargoLideranca>Vice-Líder</descricaoCargoLideranca>
        <numOrdemCargo>38</numOrdemCargo>
        <dataDesignacao>25/11/2009</dataDesignacao>
        <dataTermino>12/03/2010</dataTermino>
        <codigoUnidadeLideranca>P</codigoUnidadeLideranca>
        <siglaUnidadeLideranca>PSDB</siglaUnidadeLideranca>
        <idBlocoPartido>PSDB</idBlocoPartido>
      </itemHistoricoLider>
    </historicoLider>
  </Deputado>
</Deputados>